lettrade/__init__.py
lettrade/all.py
lettrade/bot.py
lettrade/lettrade.py
lettrade/account/__init__.py
lettrade/account/account.py
lettrade/base/__init__.py
lettrade/base/error.py
lettrade/base/flag.py
lettrade/brain/__init__.py
lettrade/brain/brain.py
lettrade/calendar/__init__.py
lettrade/calendar/calendar.py
lettrade/commander/__init__.py
lettrade/commander/commander.py
lettrade/commander/telegram.py
lettrade/data/__init__.py
lettrade/data/data.py
lettrade/data/feeder.py
lettrade/data/replay.py
lettrade/data/resample.py
lettrade/data/timeframe.py
lettrade/data/wrapper.py
lettrade/data/extra/__init__.py
lettrade/data/extra/csv.py
lettrade/exchange/__init__.py
lettrade/exchange/base.py
lettrade/exchange/error.py
lettrade/exchange/exchange.py
lettrade/exchange/execute.py
lettrade/exchange/order.py
lettrade/exchange/position.py
lettrade/exchange/trade.py
lettrade/exchange/backtest/__init__.py
lettrade/exchange/backtest/account.py
lettrade/exchange/backtest/backtest.py
lettrade/exchange/backtest/commander.py
lettrade/exchange/backtest/data.py
lettrade/exchange/backtest/exchange.py
lettrade/exchange/backtest/feeder.py
lettrade/exchange/backtest/stats.py
lettrade/exchange/backtest/trade.py
lettrade/exchange/backtest/extra/__init__.py
lettrade/exchange/backtest/extra/yfinance.py
lettrade/exchange/backtest/plotly/__init__.py
lettrade/exchange/backtest/plotly/plotly_optimize.py
lettrade/exchange/live/__init__.py
lettrade/exchange/live/account.py
lettrade/exchange/live/api.py
lettrade/exchange/live/data.py
lettrade/exchange/live/exchange.py
lettrade/exchange/live/feeder.py
lettrade/exchange/live/live.py
lettrade/exchange/live/trade.py
lettrade/exchange/live/ccxt/__init__.py
lettrade/exchange/live/ccxt/api.py
lettrade/exchange/live/ccxt/ccxt.py
lettrade/exchange/live/metatrader/__init__.py
lettrade/exchange/live/metatrader/api.py
lettrade/exchange/live/metatrader/metatrader.py
lettrade/indicator/__init__.py
lettrade/indicator/function.py
lettrade/indicator/indicator.py
lettrade-0.0.3.dist-info/LICENSE
lettrade-0.0.3.dist-info/METADATA
lettrade-0.0.3.dist-info/WHEEL
lettrade-0.0.3.dist-info/top_level.txt
lettrade-0.0.3.dist-info/RECORD
