Metadata-Version: 2.1
Name: lettrade
Version: 0.0.3
Summary: Lightweight trading framwork
Home-page: https://github.com/AwesomeTrading/lettrade
Author: Santatic
Classifier: Intended Audience :: Financial and Insurance Industry
Classifier: Intended Audience :: Science/Research
Classifier: License :: OSI Approved :: GNU Affero General Public License v3 or later (AGPLv3+)
Classifier: Operating System :: OS Independent
Classifier: Programming Language :: Python :: 3 :: Only
Classifier: Programming Language :: Python :: 3.8
Classifier: Programming Language :: Python :: 3.9
Classifier: Programming Language :: Python :: 3.10
Classifier: Programming Language :: Python :: 3.11
Classifier: Programming Language :: Python :: 3.12
Classifier: Topic :: Office/Business :: Financial :: Investment
Classifier: Topic :: Scientific/Engineering :: Visualization
Requires-Python: >=3.8.0,<3.13
License-File: LICENSE
Requires-Dist: pandas
Requires-Dist: numpy
Provides-Extra: backtest
Requires-Dist: tqdm ; extra == 'backtest'
Requires-Dist: plotly ; extra == 'backtest'
Provides-Extra: backtest-extra
Requires-Dist: yfinance ; extra == 'backtest-extra'
Provides-Extra: commander
Requires-Dist: python-telegram-bot ; extra == 'commander'
Provides-Extra: dev
Requires-Dist: yfinance ; extra == 'dev'
Requires-Dist: pytz ; extra == 'dev'
Provides-Extra: exchange-ccxt
Requires-Dist: ccxt ; extra == 'exchange-ccxt'
Provides-Extra: exchange-metatrader
Provides-Extra: extra
Requires-Dist: pandas-ta ; extra == 'extra'
Requires-Dist: plotly ; extra == 'extra'
Requires-Dist: nbformat ; extra == 'extra'
